{
    "exercise": {

        "id": 1234,
        "actions": [

            {

                "name": "OMG! OMG! OMG!",
                "icon": "heart",
                "positions": [

                    {
                        "begin": "0:30",
                        "end": "0:45"
                    },

                    {
                        "begin": "2:30",
                        "end": "2:50"
                    }

                ],
                "cooldown": 3,
                "limits": 5

            },

            {

                "name": "Shut up! ... and take my money!",
                "icon": "",
                "positions": [

                    {
                        "begin": "1:00",
                        "end": "1:30"
                    },

                    {
                        "begin": "3:15",
                        "end": "3:35"
                    }

                ],
                "cooldown": 3,
                "limits": 4

            },

            {

                "name": "Pew! Pew!",
                "icon": "pacman",
                "positions": [

                    {
                        "begin": "1:00",
                        "end": "1:30"
                    },

                    {
                        "begin": "3:15",
                        "end": "3:35"
                    }

                ],
                "cooldown": 6,
                "limits": 1

            },

            {

                "name": "Excited!",
                "icon": "grin",
                "positions": [

                    {
                        "begin": "1:00",
                        "end": "1:30"
                    },

                    {
                        "begin": "3:15",
                        "end": "3:35"
                    }

                ],
                "cooldown": 4,
                "limits": 5

            },

            {

                "name": "Power up!",
                "icon": "power",
                "positions": [

                    {
                        "begin": "1:00",
                        "end": "1:30"
                    },

                    {
                        "begin": "3:15",
                        "end": "3:35"
                    }

                ],
                "cooldown": 3,
                "limits": 3

            }

        ]

    }

}